SwarmNode.v
module SwarmNode (
    clk,
    rst_n,
    spike_in,
    decay_pulse,
    data_a,
    data_b,
    mac_en,
    mac_clr,
    mac_out,
    stress_reg
);

    // 1. Port Directions
    input         clk;
    input         rst_n;
    input         spike_in;
    input         decay_pulse;
    input  [7:0]  data_a;
    input  [7:0]  data_b;
    input         mac_en;
    input         mac_clr;
    output [15:0] mac_out;
    output [7:0]  stress_reg;

    // 2. Data Type Definitions
    reg [15:0] mac_out;
    reg [7:0]  stress_reg;
    reg [15:0] accumulator;
    wire [15:0] product;

    // 3. STRESS LOGIC (Homeostasis)
    always @(posedge clk or negedge rst_n) begin
        if (!rst_n) begin
            stress_reg <= 8'h00;
        end else begin
            if (spike_in && (stress_reg < 8'hFF)) begin
                stress_reg <= (stress_reg > 8'd250) ? 8'hFF : (stress_reg + 8'd5);
            end else if (decay_pulse && (stress_reg > 0)) begin
                stress_reg <= stress_reg - 8'd1;
            end
        end
    end

    // 4. MAC UNIT
    assign product = data_a * data_b;

    always @(posedge clk or negedge rst_n) begin
        if (!rst_n) begin
            accumulator <= 16'h0000;
        end else if (mac_clr) begin
            accumulator <= 16'h0000;
        end else if (mac_en) begin
            accumulator <= accumulator + product;
        end
    end

    // 5. ADAPTIVE PRECISION (Biomimetic Power Saving)
    // Zeroes the 8 LSBs when stressed to reduce switching activity (alpha)
    always @(*) begin
        if (stress_reg > 8'd200) begin
            mac_out = {accumulator[15:8], 8'h00}; 
        end else begin
            mac_out = accumulator;
        end
    end

endmodule

ENTROPY/TopGrid.v
module TopGrid (
    clk,
    rst_n,
    spike_in_data_a,
    spike_in_data_b,
    spike_in_valid,
    fault_inject,
    spike_out_final
);

    input         clk;
    input         rst_n;
    input  [7:0]  spike_in_data_a;
    input  [7:0]  spike_in_data_b;
    input         spike_in_valid;
    input         fault_inject;
    output [15:0] spike_out_final;

    wire [7:0]  node00_stress;
    wire        backpressure;
    wire [15:0] n00_out, n01_out;

    assign backpressure = (node00_stress > 8'd200) || fault_inject;

    wire [7:0] n00_a = (!backpressure && spike_in_valid) ? spike_in_data_a : 8'd0;
    wire [7:0] n01_a = (backpressure && spike_in_valid)  ? spike_in_data_a : 8'd0;

    SwarmNode n00 (.clk(clk), .rst_n(rst_n), .spike_in(spike_in_valid), .decay_pulse(1'b0), .data_a(n00_a), .data_b(spike_in_data_b), .mac_en(spike_in_valid), .mac_clr(1'b0), .mac_out(n00_out), .stress_reg(node00_stress));
    SwarmNode n01 (.clk(clk), .rst_n(rst_n), .spike_in(backpressure), .decay_pulse(1'b0), .data_a(n01_a), .data_b(spike_in_data_b), .mac_en(backpressure), .mac_clr(1'b0), .mac_out(n01_out), .stress_reg());
    SwarmNode n11 (.clk(clk), .rst_n(rst_n), .spike_in(1'b1), .decay_pulse(1'b0), .data_a(8'd1), .data_b(8'd1), .mac_en(1'b1), .mac_clr(1'b0), .mac_out(spike_out_final), .stress_reg());

endmodule

ENTROPY/SystemLevel_tb.v
`timescale 1ns/1ps
module SystemLevel_tb;
    reg clk, rst_n, in_v, fault;
    reg [7:0] in_a, in_b;
    wire [15:0] out_f;

    TopGrid dut (.clk(clk), .rst_n(rst_n), .spike_in_data_a(in_a), .spike_in_data_b(in_b), .spike_in_valid(in_v), .fault_inject(fault), .spike_out_final(out_f));

    always #5 clk = ~clk;

    initial begin
        $dumpfile("swarm_sim.vcd"); $dumpvars(0, SystemLevel_tb);
        clk=0; rst_n=0; in_v=0; in_a=0; in_b=0; fault=0;
        #20 rst_n=1;
        #10 in_v=1; in_a=8'd10; in_b=8'd5;
        #100 fault=1; // Trigger Reroute
        #100 $finish;
    end
endmodule

swarm_sim.vcd
$date
	Sun Feb 08 22:58:19 2026
$end
$version
	Icarus Verilog
$end
$timescale
	1ps
$end
$scope module SystemLevel_tb $end
$var wire 16 ! out_f [15:0] $end
$var reg 1 " clk $end
$var reg 1 # fault $end
$var reg 8 $ in_a [7:0] $end
$var reg 8 % in_b [7:0] $end
$var reg 1 & in_v $end
$var reg 1 ' rst_n $end
$scope module dut $end
$var wire 1 ( backpressure $end
$var wire 1 " clk $end
$var wire 1 # fault_inject $end
$var wire 1 ' rst_n $end
$var wire 8 ) spike_in_data_a [7:0] $end
$var wire 8 * spike_in_data_b [7:0] $end
$var wire 1 & spike_in_valid $end
$var wire 16 + spike_out_final [15:0] $end
$var wire 8 , node00_stress [7:0] $end
$var wire 16 - n01_out [15:0] $end
$var wire 8 . n01_a [7:0] $end
$var wire 16 / n00_out [15:0] $end
$var wire 8 0 n00_a [7:0] $end
$scope module n00 $end
$var wire 1 " clk $end
$var wire 8 1 data_a [7:0] $end
$var wire 8 2 data_b [7:0] $end
$var wire 1 3 decay_pulse $end
$var wire 1 4 mac_clr $end
$var wire 1 & mac_en $end
$var wire 1 ' rst_n $end
$var wire 1 & spike_in $end
$var wire 16 5 product [15:0] $end
$var reg 16 6 accumulator [15:0] $end
$var reg 16 7 mac_out [15:0] $end
$var reg 8 8 stress_reg [7:0] $end
$upscope $end
$scope module n01 $end
$var wire 1 " clk $end
$var wire 8 9 data_a [7:0] $end
$var wire 8 : data_b [7:0] $end
$var wire 1 ; decay_pulse $end
$var wire 1 < mac_clr $end
$var wire 1 ( mac_en $end
$var wire 1 ' rst_n $end
$var wire 1 ( spike_in $end
$var wire 16 = product [15:0] $end
$var reg 16 > accumulator [15:0] $end
$var reg 16 ? mac_out [15:0] $end
$var reg 8 @ stress_reg [7:0] $end
$upscope $end
$scope module n11 $end
$var wire 1 " clk $end
$var wire 8 A data_a [7:0] $end
$var wire 8 B data_b [7:0] $end
$var wire 1 C decay_pulse $end
$var wire 1 D mac_clr $end
$var wire 1 E mac_en $end
$var wire 1 ' rst_n $end
$var wire 1 F spike_in $end
$var wire 16 G product [15:0] $end
$var reg 16 H accumulator [15:0] $end
$var reg 16 I mac_out [15:0] $end
$var reg 8 J stress_reg [7:0] $end
$upscope $end
$upscope $end
$upscope $end
$enddefinitions $end
$comment Show the parameter values. $end
$dumpall
$end
#0
$dumpvars
b0 J
b0 I
b0 H
b1 G
1F
1E
0D
0C
b1 B
b1 A
b0 @
b0 ?
b0 >
b0 =
0<
0;
b0 :
b0 9
b0 8
b0 7
b0 6
b0 5
04
03
b0 2
b0 1
b0 0
b0 /
b0 .
b0 -
b0 ,
b0 +
b0 *
b0 )
0(
0'
0&
b0 %
b0 $
0#
0"
b0 !
$end
#5000
1"
#10000
0"
#15000
1"
#20000
0"
1'
#25000
b1 !
b1 +
b1 I
b1 H
b101 J
1"
#30000
b110010 5
b1010 0
b1010 1
0"
b101 %
b101 *
b101 2
b101 :
b1010 $
b1010 )
1&
#35000
b110010 /
b110010 7
b10 !
b10 +
b10 I
b101 ,
b101 8
b110010 6
b1010 J
b10 H
1"
#40000
0"
#45000
b11 !
b11 +
b11 I
b1100100 /
b1100100 7
b11 H
b1111 J
b1100100 6
b1010 ,
b1010 8
1"
#50000
0"
#55000
b10010110 /
b10010110 7
b100 !
b100 +
b100 I
b1111 ,
b1111 8
b10010110 6
b10100 J
b100 H
1"
#60000
0"
#65000
b101 !
b101 +
b101 I
b11001000 /
b11001000 7
b101 H
b11001 J
b11001000 6
b10100 ,
b10100 8
1"
#70000
0"
#75000
b11111010 /
b11111010 7
b110 !
b110 +
b110 I
b11001 ,
b11001 8
b11111010 6
b11110 J
b110 H
1"
#80000
0"
#85000
b111 !
b111 +
b111 I
b100101100 /
b100101100 7
b111 H
b100011 J
b100101100 6
b11110 ,
b11110 8
1"
#90000
0"
#95000
b101011110 /
b101011110 7
b1000 !
b1000 +
b1000 I
b100011 ,
b100011 8
b101011110 6
b101000 J
b1000 H
1"
#100000
0"
#105000
b1001 !
b1001 +
b1001 I
b110010000 /
b110010000 7
b1001 H
b101101 J
b110010000 6
b101000 ,
b101000 8
1"
#110000
0"
#115000
b111000010 /
b111000010 7
b1010 !
b1010 +
b1010 I
b101101 ,
b101101 8
b111000010 6
b110010 J
b1010 H
1"
#120000
0"
#125000
b1011 !
b1011 +
b1011 I
b111110100 /
b111110100 7
b1011 H
b110111 J
b111110100 6
b110010 ,
b110010 8
1"
#130000
b110010 =
b1010 .
b1010 9
b0 5
b0 0
b0 1
1(
0"
1#
#135000
b110010 -
b110010 ?
b1100 !
b1100 +
b1100 I
b110111 ,
b110111 8
b101 @
b110010 >
b111100 J
b1100 H
1"
#140000
0"
#145000
b1101 !
b1101 +
b1101 I
b1100100 -
b1100100 ?
b1101 H
b1000001 J
b1100100 >
b1010 @
b111100 ,
b111100 8
1"
#150000
0"
#155000
b10010110 -
b10010110 ?
b1110 !
b1110 +
b1110 I
b1000001 ,
b1000001 8
b1111 @
b10010110 >
b1000110 J
b1110 H
1"
#160000
0"
#165000
b1111 !
b1111 +
b1111 I
b11001000 -
b11001000 ?
b1111 H
b1001011 J
b11001000 >
b10100 @
b1000110 ,
b1000110 8
1"
#170000
0"
#175000
b11111010 -
b11111010 ?
b10000 !
b10000 +
b10000 I
b1001011 ,
b1001011 8
b11001 @
b11111010 >
b1010000 J
b10000 H
1"
#180000
0"
#185000
b10001 !
b10001 +
b10001 I
b100101100 -
b100101100 ?
b10001 H
b1010101 J
b100101100 >
b11110 @
b1010000 ,
b1010000 8
1"
#190000
0"
#195000
b101011110 -
b101011110 ?
b10010 !
b10010 +
b10010 I
b1010101 ,
b1010101 8
b100011 @
b101011110 >
b1011010 J
b10010 H
1"
#200000
0"
#205000
b10011 !
b10011 +
b10011 I
b110010000 -
b110010000 ?
b10011 H
b1011111 J
b110010000 >
b101000 @
b1011010 ,
b1011010 8
1"
#210000
0"
#215000
b111000010 -
b111000010 ?
b10100 !
b10100 +
b10100 I
b1011111 ,
b1011111 8
b101101 @
b111000010 >
b1100100 J
b10100 H
1"
#220000
0"
#225000
b10101 !
b10101 +
b10101 I
b111110100 -
b111110100 ?
b10101 H
b1101001 J
b111110100 >
b110010 @
b1100100 ,
b1100100 8
1"
